CHANGES.rst
CONTRIBUTORS.rst
MANIFEST.in
README.rst
VERSION
setup.cfg
setup.py
docs/LICENSE.GPL
docs/LICENSE.rst
docs/index.rst
src/visaplan/__init__.py
src/visaplan.plone.adapters.egg-info/PKG-INFO
src/visaplan.plone.adapters.egg-info/SOURCES.txt
src/visaplan.plone.adapters.egg-info/dependency_links.txt
src/visaplan.plone.adapters.egg-info/entry_points.txt
src/visaplan.plone.adapters.egg-info/namespace_packages.txt
src/visaplan.plone.adapters.egg-info/not-zip-safe
src/visaplan.plone.adapters.egg-info/requires.txt
src/visaplan.plone.adapters.egg-info/top_level.txt
src/visaplan/plone/__init__.py
src/visaplan/plone/adapters/.comments
src/visaplan/plone/adapters/__init__.py
src/visaplan/plone/adapters/configure.zcml
src/visaplan/plone/adapters/flvinfo/__init__.py
src/visaplan/plone/adapters/flvinfo/adapter.py
src/visaplan/plone/adapters/flvinfo/configure.zcml
src/visaplan/plone/adapters/flvinfo/flvlib/__init__.py
src/visaplan/plone/adapters/flvinfo/flvlib/astypes.py
src/visaplan/plone/adapters/flvinfo/flvlib/constants.py
src/visaplan/plone/adapters/flvinfo/flvlib/helpers.py
src/visaplan/plone/adapters/flvinfo/flvlib/primitives.py
src/visaplan/plone/adapters/flvinfo/flvlib/tags.py
src/visaplan/plone/adapters/flvinfo/flvlib/scripts/__init__.py
src/visaplan/plone/adapters/flvinfo/flvlib/scripts/debug_flv.py
src/visaplan/plone/adapters/flvinfo/flvlib/scripts/index_flv.py
src/visaplan/plone/adapters/flvinfo/flvlib/scripts/retimestamp_flv.py
src/visaplan/plone/adapters/getmenulevel/__init__.py
src/visaplan/plone/adapters/getmenulevel/adapter.py
src/visaplan/plone/adapters/getmenulevel/configure.zcml
src/visaplan/plone/adapters/grouplog/__init__.py
src/visaplan/plone/adapters/grouplog/adapter.py
src/visaplan/plone/adapters/grouplog/configure.zcml
src/visaplan/plone/adapters/grouplog/utils.py
src/visaplan/plone/adapters/pc2/__init__.py
src/visaplan/plone/adapters/pc2/adapter.py
src/visaplan/plone/adapters/pc2/configure.zcml
src/visaplan/plone/adapters/pformat/__init__.py
src/visaplan/plone/adapters/pformat/adapter.py
src/visaplan/plone/adapters/pformat/configure.zcml
src/visaplan/plone/adapters/puc/__init__.py
src/visaplan/plone/adapters/puc/adapter.py
src/visaplan/plone/adapters/puc/configure.zcml
src/visaplan/plone/adapters/rawbyname/__init__.py
src/visaplan/plone/adapters/rawbyname/adapter.py
src/visaplan/plone/adapters/rawbyname/configure.zcml
